impuls-2.4.1.dist-info/METADATA
impuls-2.4.1.dist-info/WHEEL
impuls/extern/libextern.so
impuls/extern/__init__.py
impuls/model/meta/__init__.py
impuls/model/meta/entity.py
impuls/model/meta/extra_fields_mixin.py
impuls/model/meta/sql_builder.py
impuls/model/meta/utility_types.py
impuls/model/__init__.py
impuls/model/agency.py
impuls/model/attribution.py
impuls/model/calendar_exception.py
impuls/model/calendar.py
impuls/model/extra_table_row.py
impuls/model/fare_attribute.py
impuls/model/fare_rule.py
impuls/model/feed_info.py
impuls/model/frequency.py
impuls/model/route.py
impuls/model/shape_point.py
impuls/model/stop.py
impuls/model/stop_time.py
impuls/model/transfer.py
impuls/model/translation.py
impuls/model/trip.py
impuls/tasks/__init__.py
impuls/tasks/add_entity.py
impuls/tasks/assign_directions.py
impuls/tasks/exec_sql.py
impuls/tasks/extend_calendars.py
impuls/tasks/generate_trip_headsign.py
impuls/tasks/load_busman.py
impuls/tasks/load_db.py
impuls/tasks/load_gtfs.py
impuls/tasks/merge.py
impuls/tasks/modify_from_csv.py
impuls/tasks/remove_unused_entities.py
impuls/tasks/save_db.py
impuls/tasks/save_gtfs.py
impuls/tasks/simplify_calendars.py
impuls/tasks/split_trip_legs.py
impuls/tasks/truncate_calendars.py
impuls/tools/__init__.py
impuls/tools/color.py
impuls/tools/geo.py
impuls/tools/iteration.py
impuls/tools/logs.py
impuls/tools/machine_load.py
impuls/tools/polish_calendar_exceptions.py
impuls/tools/strings.py
impuls/tools/temporal.py
impuls/tools/testing_mocks.py
impuls/tools/types.py
impuls/__init__.py
impuls/app.py
impuls/db.py
impuls/errors.py
impuls/multi_file.py
impuls/options.py
impuls/pipeline.py
impuls/py.typed
impuls/resource.py
impuls/selector.py
impuls/task.py
impuls-2.4.1.dist-info/RECORD
