Metadata-Version: 2.1
Name: impuls
Version: 2.4.1
Author-Email: =?utf-8?q?Miko=C5=82aj_Kuranowski?= <mkuranowski@gmail.com>
Requires-Python: ~=3.10
Requires-Dist: requests~=2.32
Requires-Dist: pyyaml~=6.0
Requires-Dist: typing_extensions~=4.1
